napari_deepspot/__init__.py
napari_deepspot/_dock_widget.py
napari_deepspot/_version.py
napari_deepspot/deepSpot_functions.py
napari_deepspot/_tests/__init__.py
napari_deepspot/_tests/test_dock_widget.py
napari_deepspot/_tests/test_function.py
napari_deepspot/models/MHybrid/saved_model.pb
napari_deepspot/models/MHybrid/variables/variables.data-00000-of-00001
napari_deepspot/models/MHybrid/variables/variables.index
napari_deepspot/models/newmodel/saved_model.pb
napari_deepspot/models/newmodel/variables/variables.data-00000-of-00001
napari_deepspot/models/newmodel/variables/variables.index
napari_DeepSpot-0.0.7.dist-info/LICENSE
napari_DeepSpot-0.0.7.dist-info/METADATA
napari_DeepSpot-0.0.7.dist-info/WHEEL
napari_DeepSpot-0.0.7.dist-info/entry_points.txt
napari_DeepSpot-0.0.7.dist-info/top_level.txt
napari_DeepSpot-0.0.7.dist-info/RECORD
