Metadata-Version: 2.1
Name: napari-DeepSpot
Version: 0.0.7
Summary: RNA spot enhancement for fluorescent microscopy images
Home-page: https://github.com/ebouilhol/napari-DeepSpot
Author: Emmanuel Bouilhol
Author-email: emmanuel.bouilhol@u-bordeaux.fr
License: MIT
Project-URL: Bug Tracker, https://github.com/ebouilhol/napari-DeepSpot/issues
Project-URL: Documentation, https://github.com/ebouilhol/napari-DeepSpot#README.md
Project-URL: Source Code, https://github.com/ebouilhol/napari-DeepSpot
Project-URL: User Support, https://github.com/ebouilhol/napari-DeepSpot/issues
Platform: UNKNOWN
Classifier: Development Status :: 2 - Pre-Alpha
Classifier: Intended Audience :: Developers
Classifier: Framework :: napari
Classifier: Topic :: Software Development :: Testing
Classifier: Programming Language :: Python
Classifier: Programming Language :: Python :: 3
Classifier: Programming Language :: Python :: 3.7
Classifier: Programming Language :: Python :: 3.8
Classifier: Programming Language :: Python :: 3.9
Classifier: Operating System :: OS Independent
Classifier: License :: OSI Approved :: MIT License
Requires-Python: >=3.7
License-File: LICENSE
Requires-Dist: napari-plugin-engine (>=0.1.4)
Requires-Dist: numpy
Requires-Dist: pytest
Requires-Dist: pytest-cov
Requires-Dist: pytest-xvfb
Requires-Dist: pytest-qt
Requires-Dist: napari
Requires-Dist: qtpy (==1.9.0)
Requires-Dist: pyqt5
Requires-Dist: tensorflow
Requires-Dist: scikit-image
Requires-Dist: opencv-python
